binance_sdk_algo/__init__.py
binance_sdk_algo/algo.py
binance_sdk_algo/metadata.py
binance_sdk_algo/rest_api/__init__.py
binance_sdk_algo/rest_api/api/__init__.py
binance_sdk_algo/rest_api/api/future_algo_api.py
binance_sdk_algo/rest_api/api/spot_algo_api.py
binance_sdk_algo/rest_api/models/__init__.py
binance_sdk_algo/rest_api/models/cancel_algo_order_future_algo_response.py
binance_sdk_algo/rest_api/models/cancel_algo_order_spot_algo_response.py
binance_sdk_algo/rest_api/models/enums.py
binance_sdk_algo/rest_api/models/query_current_algo_open_orders_future_algo_response.py
binance_sdk_algo/rest_api/models/query_current_algo_open_orders_future_algo_response_orders_inner.py
binance_sdk_algo/rest_api/models/query_current_algo_open_orders_spot_algo_response.py
binance_sdk_algo/rest_api/models/query_current_algo_open_orders_spot_algo_response_orders_inner.py
binance_sdk_algo/rest_api/models/query_historical_algo_orders_future_algo_response.py
binance_sdk_algo/rest_api/models/query_historical_algo_orders_future_algo_response_orders_inner.py
binance_sdk_algo/rest_api/models/query_historical_algo_orders_spot_algo_response.py
binance_sdk_algo/rest_api/models/query_historical_algo_orders_spot_algo_response_orders_inner.py
binance_sdk_algo/rest_api/models/query_sub_orders_future_algo_response.py
binance_sdk_algo/rest_api/models/query_sub_orders_future_algo_response_sub_orders_inner.py
binance_sdk_algo/rest_api/models/query_sub_orders_spot_algo_response.py
binance_sdk_algo/rest_api/models/time_weighted_average_price_future_algo_response.py
binance_sdk_algo/rest_api/models/time_weighted_average_price_spot_algo_response.py
binance_sdk_algo/rest_api/models/volume_participation_future_algo_response.py
binance_sdk_algo/rest_api/rest_api.py
binance_sdk_algo-2.2.0.dist-info/METADATA
binance_sdk_algo-2.2.0.dist-info/WHEEL
binance_sdk_algo-2.2.0.dist-info/licenses/LICENCE
binance_sdk_algo-2.2.0.dist-info/RECORD
